<!DOCTYPE ejb-jar PUBLIC '-//Sun Microsystems, Inc.//DTD Enterprise JavaBeans 2.0//EN' 'http://java.sun.com/dtd/ejb-jar_2_0.dtd'>


<ejb-jar>
  <enterprise-beans>
    <!-- MISAST START -->
        <session>
            <display-name>AS_BASE_1000EJB</display-name>
            <ejb-name>AS_BASE_1000EJB</ejb-name>
            <home>chosun.ciis.as.base.ejb.AS_BASE_1000EJBHome</home>
            <remote>chosun.ciis.as.base.ejb.AS_BASE_1000EJB</remote>
            <ejb-class>chosun.ciis.as.base.ejb.AS_BASE_1000EJBBean</ejb-class>
            <session-type>Stateless</session-type>
            <transaction-type>Container</transaction-type>
        </session>
        <session>
            <display-name>AS_ARTMGR_1000EJB</display-name>
            <ejb-name>AS_ARTMGR_1000EJB</ejb-name>
            <home>chosun.ciis.as.artmgr.ejb.AS_ARTMGR_1000EJBHome</home>
            <remote>chosun.ciis.as.artmgr.ejb.AS_ARTMGR_1000EJB</remote>
            <ejb-class>chosun.ciis.as.artmgr.ejb.AS_ARTMGR_1000EJBBean</ejb-class>
            <session-type>Stateless</session-type>
            <transaction-type>Container</transaction-type>
        </session>
        <session>
            <display-name>AS_ASET_1000EJB</display-name>
            <ejb-name>AS_ASET_1000EJB</ejb-name>
            <home>chosun.ciis.as.aset.ejb.AS_ASET_1000EJBHome</home>
            <remote>chosun.ciis.as.aset.ejb.AS_ASET_1000EJB</remote>
            <ejb-class>chosun.ciis.as.aset.ejb.AS_ASET_1000EJBBean</ejb-class>
            <session-type>Stateless</session-type>
            <transaction-type>Container</transaction-type>
        </session> 
        <session>
            <display-name>AS_ASRD_1000EJB</display-name>
            <ejb-name>AS_ASRD_1000EJB</ejb-name>
            <home>chosun.ciis.as.asrd.ejb.AS_ASRD_1000EJBHome</home>
            <remote>chosun.ciis.as.asrd.ejb.AS_ASRD_1000EJB</remote>
            <ejb-class>chosun.ciis.as.asrd.ejb.AS_ASRD_1000EJBBean</ejb-class>
            <session-type>Stateless</session-type>
            <transaction-type>Container</transaction-type>
        </session> 
        <session>
            <display-name>AS_COM_1000EJB</display-name>
            <ejb-name>AS_COM_1000EJB</ejb-name>
            <home>chosun.ciis.as.com.ejb.AS_COM_1000EJBHome</home>
            <remote>chosun.ciis.as.com.ejb.AS_COM_1000EJB</remote>
            <ejb-class>chosun.ciis.as.com.ejb.AS_COM_1000EJBBean</ejb-class>
            <session-type>Stateless</session-type>
            <transaction-type>Container</transaction-type>
        </session> 
		<session>
            <display-name>AS_LEAS_1000EJB</display-name>
            <ejb-name>AS_LEAS_1000EJB</ejb-name>
            <home>chosun.ciis.as.leas.ejb.AS_LEAS_1000EJBHome</home>
            <remote>chosun.ciis.as.leas.ejb.AS_LEAS_1000EJB</remote>
            <ejb-class>chosun.ciis.as.leas.ejb.AS_LEAS_1000EJBBean</ejb-class>
            <session-type>Stateless</session-type>
            <transaction-type>Container</transaction-type>
        </session>
        <session>
            <display-name>AS_LEAR_1000EJB</display-name>
            <ejb-name>AS_LEAR_1000EJB</ejb-name>
            <home>chosun.ciis.as.lear.ejb.AS_LEAR_1000EJBHome</home>
            <remote>chosun.ciis.as.lear.ejb.AS_LEAR_1000EJB</remote>
            <ejb-class>chosun.ciis.as.lear.ejb.AS_LEAR_1000EJBBean</ejb-class>
            <session-type>Stateless</session-type>
            <transaction-type>Container</transaction-type>
        </session>
		<session>
            <display-name>AS_REDM_1000EJB</display-name>
            <ejb-name>AS_REDM_1000EJB</ejb-name>
            <home>chosun.ciis.as.redm.ejb.AS_REDM_1000EJBHome</home>
            <remote>chosun.ciis.as.redm.ejb.AS_REDM_1000EJB</remote>
            <ejb-class>chosun.ciis.as.redm.ejb.AS_REDM_1000EJBBean</ejb-class>
            <session-type>Stateless</session-type>
            <transaction-type>Container</transaction-type>
        </session>
    <!-- MISAST END -->
  </enterprise-beans>




  <assembly-descriptor>	
    <!-- MISAST START -->
        <container-transaction>
            <method>
                <ejb-name>AS_BASE_1000EJB</ejb-name>
                <method-name>*</method-name>
            </method>
            <trans-attribute>Required</trans-attribute>
        </container-transaction>
        <container-transaction>
            <method>
                <ejb-name>AS_ARTMGR_1000EJB</ejb-name>
                <method-name>*</method-name>
            </method>
            <trans-attribute>Required</trans-attribute>
        </container-transaction>
        <container-transaction>
            <method>
                <ejb-name>AS_ASET_1000EJB</ejb-name>
                <method-name>*</method-name>
            </method>
            <trans-attribute>Required</trans-attribute>
        </container-transaction>
        <container-transaction>
            <method>
                <ejb-name>AS_ASRD_1000EJB</ejb-name>
                <method-name>*</method-name>
            </method>
            <trans-attribute>Required</trans-attribute>
        </container-transaction>
        <container-transaction>
            <method>
                <ejb-name>AS_COM_1000EJB</ejb-name>
                <method-name>*</method-name>
            </method>
            <trans-attribute>Required</trans-attribute>
        </container-transaction>
		<container-transaction>
            <method>
                <ejb-name>AS_LEAS_1000EJB</ejb-name>
                <method-name>*</method-name>
            </method>
            <trans-attribute>Required</trans-attribute>
        </container-transaction>
        <container-transaction>
            <method>
                <ejb-name>AS_LEAR_1000EJB</ejb-name>
                <method-name>*</method-name>
            </method>
            <trans-attribute>Required</trans-attribute>
        </container-transaction>
		<container-transaction>
            <method>
                <ejb-name>AS_REDM_1000EJB</ejb-name>
                <method-name>*</method-name>
            </method>
            <trans-attribute>Required</trans-attribute>
        </container-transaction>
    <!-- MISAST END -->
  </assembly-descriptor>

</ejb-jar>
